genisys/__futures__.py
genisys/__init__.py
genisys/__main__.py
genisys/_compat.py
genisys/console/__init__.py
genisys/console/create.py
genisys/console/deinit.py
genisys/console/deps.py
genisys/console/env.py
genisys/console/init.py
genisys/console/install.py
genisys/console/templates/plugin.zip
genisys/console/templates/project.zip
genisys/console/templates/workspace.zip
genisys/console/utils.py
genisys/env.py
genisys/errors.py
genisys/utils/__init__.py
genisys/utils/imports.py
genisys/utils/merging.py
genisys-0.1.2.dist-info/entry_points.txt
genisys-0.1.2.dist-info/LICENSE
genisys-0.1.2.dist-info/WHEEL
genisys-0.1.2.dist-info/METADATA
genisys-0.1.2.dist-info/RECORD
